jupyter_federation/__init__.py
jupyter_federation/version.py
jupyter_federation-0.0.3.dist-info/METADATA
jupyter_federation-0.0.3.dist-info/WHEEL
jupyter_federation-0.0.3.dist-info/top_level.txt
jupyter_federation-0.0.3.dist-info/zip-safe
jupyter_federation-0.0.3.dist-info/RECORD
